Workbook
Name Aporte: APLICAÇÕES!$D$16
Name Patrimonio: APLICAÇÕES!$D$19
Name Qtd_Anos: APLICAÇÕES!$D$17
Name Rendimento_Carteira: APLICAÇÕES!$D$12
Name salario: APLICAÇÕES!$D$11
Name Sugestao_investimento: APLICAÇÕES!$D$13
Name Taxa_Mensal: APLICAÇÕES!$D$18

Sheet APLICAÇÕES
B10: CONFIGURAÇÕES
B11: Salário | D11: 3800
B12: Rendimento carteira | D12: 0.009
B13: Sugestão de Investimento (20%) | D13: =D11*20% -> 760
B15: INVESTIMENTOS MENSAIS
B16: Quanto investir por mês? | D16: 760
B17: Por quantos anos? | D17: 10
B18: Taxa de rendimento mensal? | D18: 0.01079
B19: Patrimônio acumulado? | D19: =FV(Taxa_Mensal,Qtd_Anos*12,Aporte*-1) -> 184896
B20: Dividendos mensais? | D20: =Patrimonio*Rendimento_Carteira -> 1664.064
B22: CENÁRIOS | D22: DIVIDENDOS
A23: 2 | B23: Quantos em 2 anos? | C23: =FV($D$18,$A23*12,$D$16*-1) -> 20692.997 | D23: =C23*Rendimento_Carteira -> 186.23697
A24: 5 | B24: Quantos em 5 anos? | C24: =FV($D$18,$A24*12,$D$16*-1) -> 63670.455 | D24: =C24*Rendimento_Carteira -> 573.03409
A25: 10 | B25: Quantos em 10 anos? | C25: =FV($D$18,$A25*12,$D$16*-1) -> 184896 | D25: =C25*Rendimento_Carteira -> 1664.064
A26: 20 | B26: Quantos em 20 anos? | C26: =FV($D$18,$A26*12,$D$16*-1) -> 855150.78 | D26: =C26*Rendimento_Carteira -> 7696.3571
A27: 30 | B27: Quantos em 30 anos? | C27: =FV($D$18,$A27*12,$D$16*-1) -> 3284848.9 | D27: =C27*Rendimento_Carteira -> 29563.64
B30: PERFIL | C30: MODERADO
B31: Valor a ser investido por mês | C31: =Aporte -> 760
B33: TIPO DE FII | C33: PERCENTUAL SUGERIDO | D33: VALORES
B34: PAPEL | C34: =VLOOKUP($C$30&"-"&B34,FORMULAÇÕES!$A:$D,4,FALSE) -> 0.32 | D34: =C34*$C$31 -> 243.2
B35: TIJOLO | C35: =VLOOKUP($C$30&"-"&B35,FORMULAÇÕES!$A:$D,4,FALSE) -> 0.35 | D35: =C35*$C$31 -> 266
B36: HÍBRIDOS | C36: =VLOOKUP($C$30&"-"&B36,FORMULAÇÕES!$A:$D,4,FALSE) -> 0.08 | D36: =C36*$C$31 -> 60.8
B37: FOFs | C37: =VLOOKUP($C$30&"-"&B37,FORMULAÇÕES!$A:$D,4,FALSE) -> 0.05 | D37: =C37*$C$31 -> 38
B38: DESENVOLVIMENTO | C38: =VLOOKUP($C$30&"-"&B38,FORMULAÇÕES!$A:$D,4,FALSE) -> 0.1 | D38: =C38*$C$31 -> 76
B39: HOTELARIAS | C39: =VLOOKUP($C$30&"-"&B39,FORMULAÇÕES!$A:$D,4,FALSE) -> 0.1 | D39: =C39*$C$31 -> 76
D40: =SUM(D34:D39) -> 760

Sheet FORMULAÇÕES
A1: CHAVE | B1: PERFIL | C1: TIPO DE FII | D1: PERCENTUAL %
A2: =$B$2&"-"&C2 -> CONSERVADOR-PAPEL | B2: CONSERVADOR | C2: PAPEL | D2: 0.3
A3: =$B$2&"-"&C3 -> CONSERVADOR-TIJOLO | B3: CONSERVADOR | C3: TIJOLO | D3: 0.5
A4: =$B$2&"-"&C4 -> CONSERVADOR-HÍBRIDOS | B4: CONSERVADOR | C4: HÍBRIDOS | D4: 0.07
A5: =$B$2&"-"&C5 -> CONSERVADOR-FOFs | B5: CONSERVADOR | C5: FOFs | D5: 0.05
A6: =$B$2&"-"&C6 -> CONSERVADOR-DESENVOLVIMENTO | B6: CONSERVADOR | C6: DESENVOLVIMENTO | D6: 0.05
A7: =$B$2&"-"&C7 -> CONSERVADOR-HOTELARIAS | B7: CONSERVADOR | C7: HOTELARIAS | D7: 0.03
A8: =$B$8&"-"&C8 -> MODERADO-PAPEL | B8: MODERADO | C8: PAPEL | D8: 0.32
A9: =$B$8&"-"&C9 -> MODERADO-TIJOLO | B9: MODERADO | C9: TIJOLO | D9: 0.35
A10: =$B$8&"-"&C10 -> MODERADO-HÍBRIDOS | B10: MODERADO | C10: HÍBRIDOS | D10: 0.08
A11: =$B$8&"-"&C11 -> MODERADO-FOFs | B11: MODERADO | C11: FOFs | D11: 0.05
A12: =$B$8&"-"&C12 -> MODERADO-DESENVOLVIMENTO | B12: MODERADO | C12: DESENVOLVIMENTO | D12: 0.1
A13: =$B$8&"-"&C13 -> MODERADO-HOTELARIAS | B13: MODERADO | C13: HOTELARIAS | D13: 0.1
A14: =$B$14&"-"&C14 -> AGRESSIVO-PAPEL | B14: AGRESSIVO | C14: PAPEL | D14: 0.5
A15: =$B$14&"-"&C15 -> AGRESSIVO-TIJOLO | B15: AGRESSIVO | C15: TIJOLO | D15: 0.1
A16: =$B$14&"-"&C16 -> AGRESSIVO-HÍBRIDOS | B16: AGRESSIVO | C16: HÍBRIDOS | D16: 0.05
A17: =$B$14&"-"&C17 -> AGRESSIVO-FOFs | B17: AGRESSIVO | C17: FOFs | D17: 0.05
A18: =$B$14&"-"&C18 -> AGRESSIVO-DESENVOLVIMENTO | B18: AGRESSIVO | C18: DESENVOLVIMENTO | D18: 0.2
A19: =$B$14&"-"&C19 -> AGRESSIVO-HOTELARIAS | B19: AGRESSIVO | C19: HOTELARIAS | D19: 0.1
